Deformation3D/__init__.py
Deformation3D/deform.cpython-310-x86_64-linux-gnu.so
Deformation3D/deform.cpython-38-x86_64-linux-gnu.so
Deformation3D/deformation3d.py
Deformation3D/demo.py
Deformation3D/generate_vox.py
Deformation3D/obj_2_points.py
deformation3d-1.8.1.dist-info/METADATA
deformation3d-1.8.1.dist-info/WHEEL
deformation3d-1.8.1.dist-info/top_level.txt
deformation3d-1.8.1.dist-info/RECORD
