Metadata-Version: 2.1
Name: deformation3d
Version: 1.8.1
Summary: Automated Batch Deformation Method for Crop 3D Point Clouds
Requires-Python: >=3.8
